zo/__init__.py
zo/config.py
zo/dex.py
zo/idl.json
zo/types.py
zo/util.py
zo/zo.py
zo_sdk-0.2.0.dist-info/LICENSE
zo_sdk-0.2.0.dist-info/WHEEL
zo_sdk-0.2.0.dist-info/METADATA
zo_sdk-0.2.0.dist-info/RECORD
