Metadata-Version: 2.1
Name: zo-sdk
Version: 0.2.0
Summary: 01.xyz Python SDK
Home-page: https://github.com/01protocol/zo-sdk-py
License: Apache-2.0
Author: Sheheryar Parvaz
Author-email: me@cherryman.org
Requires-Python: >=3.10,<4.0
Classifier: License :: OSI Approved :: Apache Software License
Classifier: Programming Language :: Python :: 3
Classifier: Programming Language :: Python :: 3.10
Requires-Dist: anchorpy (>=0.9.3,<0.10.0)
Requires-Dist: solana (>=0.25.0,<0.26.0)
Project-URL: Documentation, https://01protocol.github.io/zo-sdk-py/
Project-URL: Repository, https://github.com/01protocol/zo-sdk-py
